README.rst
setup.py
lovely/__init__.py
lovely.esdb.egg-info/PKG-INFO
lovely.esdb.egg-info/SOURCES.txt
lovely.esdb.egg-info/dependency_links.txt
lovely.esdb.egg-info/not-zip-safe
lovely.esdb.egg-info/requires.txt
lovely.esdb.egg-info/top_level.txt
lovely/esdb/__init__.py
lovely/esdb/tests.py
lovely/esdb/document/__init__.py
lovely/esdb/document/bulk.py
lovely/esdb/document/document.py
lovely/esdb/document/lazy.py
lovely/esdb/properties/__init__.py
lovely/esdb/properties/objectproperty.py
lovely/esdb/properties/property.py
lovely/esdb/properties/relation.py
lovely/esdb/properties/testing.py
lovely/esdb/testing/__init__.py