Metadata-Version: 1.0
Name: lovely.esdb
Version: 0.3.5
Summary: a simple elasticsearch document mapper
Home-page: http://lovelyesdb.readthedocs.io/en/latest/index.html
Author: lovelysystems
Author-email: office@lovelysystems.com
License: UNKNOWN
Platform: UNKNOWN
